fixtup_sqlalchemy/__init__.py
fixtup_sqlalchemy-0.0.0a0.dist-info/LICENSE
fixtup_sqlalchemy-0.0.0a0.dist-info/METADATA
fixtup_sqlalchemy-0.0.0a0.dist-info/WHEEL
fixtup_sqlalchemy-0.0.0a0.dist-info/top_level.txt
fixtup_sqlalchemy-0.0.0a0.dist-info/RECORD
