Metadata-Version: 2.1
Name: fixtup-sqlalchemy
Version: 0.0.0a0
Home-page: https://github.com/FabienArcellier/fixtup-sqlalchemy
License: MIT
Classifier: Development Status :: 3 - Alpha
Classifier: Framework :: Pytest
Classifier: Intended Audience :: Developers
Classifier: License :: OSI Approved :: MIT License
Classifier: Operating System :: OS Independent
Classifier: Programming Language :: Python
License-File: LICENSE
Provides-Extra: dev
Requires-Dist: alfred-cli ; extra == 'dev'
Requires-Dist: build ; extra == 'dev'
Requires-Dist: mypy ; extra == 'dev'
Requires-Dist: setuptools-scm ; extra == 'dev'
Requires-Dist: twine ; extra == 'dev'
